[
    {
        "author": "the guy who wrote this crap",
        "text": "you're probably wondering where all the messages went. i had to remove them because you guys spammed this server so much. or you're not wondering that but just spamming below."
    },
    {
        "author": "throwback to zoover",
        "text": "yeet"
    },
    {
        "author": "osamaosamaosamaosamaosamaosama",
        "text": "osamaosamaosamaosamaosamaosamaosamaosamaosamaosama"
    },
    {
        "author": "annoy",
        "text": "Hi anon!"
    },
    {
        "author": "Laqkjj",
        "text": "Pepeiieds"
    },
    {
        "author": "Patrick",
        "text": "Is mayonnaise an instrument?"
    },
    {
        "author": "hello",
        "text": "there"
    },
    {
        "author": "Github Issue",
        "text": "The github repo for this gives a non https link"
    },
    {
        "author": "Henk",
        "text": "Hoi !"
    },
    {
        "author": "Judge",
        "text": "Why did you have to reset the server from just a"
    },
    {
        "author": "Judge",
        "text": "Few messages"
    },
    {
        "author": "Judge",
        "text": "Are you poor or somthin?"
    }
]